torch_scalpel/__init__.py
torch_scalpel-0.1.0.dev0.dist-info/METADATA
torch_scalpel-0.1.0.dev0.dist-info/WHEEL
torch_scalpel-0.1.0.dev0.dist-info/top_level.txt
torch_scalpel-0.1.0.dev0.dist-info/RECORD
