Metadata-Version: 2.4
Name: torch-scalpel
Version: 0.1.0.dev0
Summary: PyTorch transformers meets fx graph manipulation
Requires-Python: >=3.11
Requires-Dist: einops>=0.8.1
Requires-Dist: numpy>=2.3.0
Requires-Dist: setuptools>=80.9.0
Requires-Dist: torch>=2.7.1
